{
  "project_info": {
    "project_number": "565394693454",
    "project_id": "zambia-sign-language-hub",
    "storage_bucket": "zambia-sign-language-hub.firebasestorage.app"
  },
  "client": [
    {
      "client_info": {
        "mobilesdk_app_id": "1:565394693454:android:5bd46d84165ff04c95121f",
        "android_client_info": {
          "package_name": "com.zambiasignhub"
        }
      },
      "oauth_client": [],
      "api_key": [
        {
          "current_key": "AIzaSyBgaMVVVjirkd5EKKItMcJmkD253h3h8EM"
        }
      ],
      "services": {
        "appinvite_service": {
          "other_platform_oauth_client": []
        }
      }
    }
  ],
  "configuration_version": "1"
}